{
"meta":{"test_sets":[],"test_metrics":[],"learn_metrics":[{"best_value":"Min","name":"Logloss"}],"launch_mode":"Train","parameters":"","iteration_count":100,"learn_sets":["learn"],"name":"experiment"},
"iterations":[
{"learn":[0.6607313965],"iteration":0,"passed_time":0.1467089639,"remaining_time":14.52418743},
{"learn":[0.6343531907],"iteration":1,"passed_time":0.1548463929,"remaining_time":7.58747325},
{"learn":[0.6126356383],"iteration":2,"passed_time":0.1632395908,"remaining_time":5.278080101},
{"learn":[0.5978239475],"iteration":3,"passed_time":0.1718602144,"remaining_time":4.124645146},
{"learn":[0.5828279434],"iteration":4,"passed_time":0.1803215982,"remaining_time":3.426110366},
{"learn":[0.5698277432],"iteration":5,"passed_time":0.1870101485,"remaining_time":2.92982566},
{"learn":[0.562274556],"iteration":6,"passed_time":0.1946410026,"remaining_time":2.585944749},
{"learn":[0.555682589],"iteration":7,"passed_time":0.202713979,"remaining_time":2.331210759},
{"learn":[0.5488034553],"iteration":8,"passed_time":0.2108135946,"remaining_time":2.131559679},
{"learn":[0.5426768182],"iteration":9,"passed_time":0.2185840675,"remaining_time":1.967256607},
{"learn":[0.5325717577],"iteration":10,"passed_time":0.2268473127,"remaining_time":1.835400984},
{"learn":[0.5273535685],"iteration":11,"passed_time":0.2334193374,"remaining_time":1.711741808},
{"learn":[0.5237626982],"iteration":12,"passed_time":0.2413996219,"remaining_time":1.615520547},
{"learn":[0.5211051859],"iteration":13,"passed_time":0.2499977974,"remaining_time":1.535700756},
{"learn":[0.5154964381],"iteration":14,"passed_time":0.2590036359,"remaining_time":1.46768727},
{"learn":[0.5124795883],"iteration":15,"passed_time":0.2666734404,"remaining_time":1.400035562},
{"learn":[0.5098675932],"iteration":16,"passed_time":0.2744989177,"remaining_time":1.340200598},
{"learn":[0.5055545006],"iteration":17,"passed_time":0.2817357118,"remaining_time":1.283462687},
{"learn":[0.5024446037],"iteration":18,"passed_time":0.2893221007,"remaining_time":1.233425798},
{"learn":[0.5005617127],"iteration":19,"passed_time":0.2969116464,"remaining_time":1.187646586},
{"learn":[0.49875367],"iteration":20,"passed_time":0.3050358545,"remaining_time":1.147515834},
{"learn":[0.497461377],"iteration":21,"passed_time":0.3129425477,"remaining_time":1.109523578},
{"learn":[0.4952876845],"iteration":22,"passed_time":0.3208175298,"remaining_time":1.074041295},
{"learn":[0.4937771897],"iteration":23,"passed_time":0.3300201266,"remaining_time":1.045063734},
{"learn":[0.49005226],"iteration":24,"passed_time":0.3427275268,"remaining_time":1.02818258},
{"learn":[0.4879469307],"iteration":25,"passed_time":0.349451551,"remaining_time":0.9945928759},
{"learn":[0.4823852019],"iteration":26,"passed_time":0.3579901741,"remaining_time":0.9678993597},
{"learn":[0.4808039133],"iteration":27,"passed_time":0.3677132157,"remaining_time":0.945548269},
{"learn":[0.4759260252],"iteration":28,"passed_time":0.3789512015,"remaining_time":0.9277770795},
{"learn":[0.4747100687],"iteration":29,"passed_time":0.3881809071,"remaining_time":0.9057554498},
{"learn":[0.4735782001],"iteration":30,"passed_time":0.3989890746,"remaining_time":0.8880724563},
{"learn":[0.4716747983],"iteration":31,"passed_time":0.4125503553,"remaining_time":0.8766695051},
{"learn":[0.4703579593],"iteration":32,"passed_time":0.425336479,"remaining_time":0.8635619422},
{"learn":[0.4693082345],"iteration":33,"passed_time":0.4372908465,"remaining_time":0.848858702},
{"learn":[0.4678754978],"iteration":34,"passed_time":0.4471543326,"remaining_time":0.8304294749},
{"learn":[0.466833259],"iteration":35,"passed_time":0.4560915545,"remaining_time":0.8108294302},
{"learn":[0.465758939],"iteration":36,"passed_time":0.4655551835,"remaining_time":0.7927020691},
{"learn":[0.464881946],"iteration":37,"passed_time":0.4764446827,"remaining_time":0.7773571139},
{"learn":[0.4640413194],"iteration":38,"passed_time":0.4867829268,"remaining_time":0.761378424},
{"learn":[0.4633723109],"iteration":39,"passed_time":0.497010503,"remaining_time":0.7455157545},
{"learn":[0.4620970819],"iteration":40,"passed_time":0.5061596276,"remaining_time":0.7283760495},
{"learn":[0.4613613776],"iteration":41,"passed_time":0.5167945692,"remaining_time":0.7136686908},
{"learn":[0.4596326728],"iteration":42,"passed_time":0.5273644685,"remaining_time":0.6990645279},
{"learn":[0.458835693],"iteration":43,"passed_time":0.5372309756,"remaining_time":0.6837485145},
{"learn":[0.4577811602],"iteration":44,"passed_time":0.5471002134,"remaining_time":0.6686780386},
{"learn":[0.4570036656],"iteration":45,"passed_time":0.5575293179,"remaining_time":0.6544909384},
{"learn":[0.4562552711],"iteration":46,"passed_time":0.5688282856,"remaining_time":0.6414446624},
{"learn":[0.4548665627],"iteration":47,"passed_time":0.578110178,"remaining_time":0.6262860262},
{"learn":[0.4529412961],"iteration":48,"passed_time":0.5889184324,"remaining_time":0.6129559195},
{"learn":[0.4520957924],"iteration":49,"passed_time":0.6017114944,"remaining_time":0.6017114944},
{"learn":[0.4516729135],"iteration":50,"passed_time":0.6123368612,"remaining_time":0.588323651},
{"learn":[0.4507193208],"iteration":51,"passed_time":0.6239096327,"remaining_time":0.575916584},
{"learn":[0.4496810253],"iteration":52,"passed_time":0.6349979101,"remaining_time":0.5631113542},
{"learn":[0.4491140992],"iteration":53,"passed_time":0.6470120426,"remaining_time":0.5511584067},
{"learn":[0.4486482881],"iteration":54,"passed_time":0.6601594044,"remaining_time":0.5401304218},
{"learn":[0.4480852306],"iteration":55,"passed_time":0.6706525876,"remaining_time":0.5269413188},
{"learn":[0.4473825868],"iteration":56,"passed_time":0.681062922,"remaining_time":0.5137843096},
{"learn":[0.4463261703],"iteration":57,"passed_time":0.6944359342,"remaining_time":0.5028674006},
{"learn":[0.4456950855],"iteration":58,"passed_time":0.7038066156,"remaining_time":0.4890859532},
{"learn":[0.4450783669],"iteration":59,"passed_time":0.7140541531,"remaining_time":0.4760361021},
{"learn":[0.4440628784],"iteration":60,"passed_time":0.7245695597,"remaining_time":0.4632493906},
{"learn":[0.4436839473],"iteration":61,"passed_time":0.7355989037,"remaining_time":0.450850941},
{"learn":[0.4429606466],"iteration":62,"passed_time":0.7457223659,"remaining_time":0.4379639292},
{"learn":[0.4423679357],"iteration":63,"passed_time":0.7615508266,"remaining_time":0.42837234},
{"learn":[0.4416603165],"iteration":64,"passed_time":0.7752146681,"remaining_time":0.4174232828},
{"learn":[0.4411709651],"iteration":65,"passed_time":0.7868294528,"remaining_time":0.4053363848},
{"learn":[0.4406414852],"iteration":66,"passed_time":0.7993837136,"remaining_time":0.3937263067},
{"learn":[0.4389626339],"iteration":67,"passed_time":0.8134776996,"remaining_time":0.3828130351},
{"learn":[0.4383570729],"iteration":68,"passed_time":0.8260245613,"remaining_time":0.3711124841},
{"learn":[0.4378932587],"iteration":69,"passed_time":0.8393398102,"remaining_time":0.3597170615},
{"learn":[0.4373260875],"iteration":70,"passed_time":0.8527825276,"remaining_time":0.3483196239},
{"learn":[0.4363941127],"iteration":71,"passed_time":0.8637228663,"remaining_time":0.3358922258},
{"learn":[0.4361201762],"iteration":72,"passed_time":0.8779293379,"remaining_time":0.3247135907},
{"learn":[0.4352031803],"iteration":73,"passed_time":0.8890385782,"remaining_time":0.3123649058},
{"learn":[0.4346655875],"iteration":74,"passed_time":0.9010555126,"remaining_time":0.3003518375},
{"learn":[0.4340621314],"iteration":75,"passed_time":0.913631706,"remaining_time":0.2885152756},
{"learn":[0.4335483229],"iteration":76,"passed_time":0.9281555515,"remaining_time":0.2772412686},
{"learn":[0.4331041033],"iteration":77,"passed_time":0.940902665,"remaining_time":0.2653828029},
{"learn":[0.4325135],"iteration":78,"passed_time":0.9512495594,"remaining_time":0.2528638069},
{"learn":[0.4321237922],"iteration":79,"passed_time":0.9630261081,"remaining_time":0.240756527},
{"learn":[0.4315693579],"iteration":80,"passed_time":0.97483513,"remaining_time":0.2286650305},
{"learn":[0.4311625251],"iteration":81,"passed_time":0.9866475889,"remaining_time":0.2165811781},
{"learn":[0.430610504],"iteration":82,"passed_time":0.9973788941,"remaining_time":0.2042824241},
{"learn":[0.4302090747],"iteration":83,"passed_time":1.009324523,"remaining_time":0.1922522902},
{"learn":[0.4297042933],"iteration":84,"passed_time":1.020723692,"remaining_time":0.1801277104},
{"learn":[0.4293094248],"iteration":85,"passed_time":1.031213951,"remaining_time":0.1678720385},
{"learn":[0.4287345133],"iteration":86,"passed_time":1.041722402,"remaining_time":0.1556596693},
{"learn":[0.4282359862],"iteration":87,"passed_time":1.053962255,"remaining_time":0.1437221257},
{"learn":[0.4276673209],"iteration":88,"passed_time":1.066215926,"remaining_time":0.1317794965},
{"learn":[0.4273820234],"iteration":89,"passed_time":1.078513274,"remaining_time":0.1198348082},
{"learn":[0.4268208736],"iteration":90,"passed_time":1.09088924,"remaining_time":0.1078901446},
{"learn":[0.4263289585],"iteration":91,"passed_time":1.102778057,"remaining_time":0.09589374407},
{"learn":[0.4258662622],"iteration":92,"passed_time":1.113592982,"remaining_time":0.08381882657},
{"learn":[0.4251991445],"iteration":93,"passed_time":1.123482099,"remaining_time":0.07171162333},
{"learn":[0.4247453053],"iteration":94,"passed_time":1.134588042,"remaining_time":0.05971516008},
{"learn":[0.4243074061],"iteration":95,"passed_time":1.146027416,"remaining_time":0.04775114234},
{"learn":[0.4238439437],"iteration":96,"passed_time":1.156685413,"remaining_time":0.03577377565},
{"learn":[0.4234581669],"iteration":97,"passed_time":1.167541421,"remaining_time":0.02382737594},
{"learn":[0.423127452],"iteration":98,"passed_time":1.179336529,"remaining_time":0.01191249019},
{"learn":[0.4227275296],"iteration":99,"passed_time":1.189761729,"remaining_time":0}
]}